{
  "id": "xiaomi_contacts",
  "course": "xiaomi",
  "title": "אנשי קשר",
  "icon": "👤",
  "difficulty": "בינוני",
  "order": 12,
  "steps": [
    {
      "title": "מוסיפים איש קשר חדש",
      "text": "פתחו את אפליקציית 'טלפון' > לשונית 'אנשי קשר' > לחצו על סמל ה-'+' > הקלידו שם ומספר טלפון > לחצו 'שמור'.",
      "warning": null
    },
    {
      "title": "מעדכנים איש קשר קיים",
      "text": "חפשו את השם בשדה החיפוש בראש המסך > לחצו עליו > לחצו על סמל העיפרון (עריכה) > שנו או הוסיפו שדות כרצונכם > לחצו 'שמור'.",
      "warning": null
    },
    {
      "title": "מוסיפים תמונה לאיש קשר",
      "text": "היכנסו לאיש הקשר > לחצו על סמל העיפרון (עריכה) > לחצו על עיגול התמונה בראש המסך > בחרו תמונה מהגלריה או צלמו תמונה חדשה > לחצו 'שמור'.",
      "warning": null
    },
    {
      "title": "מעבירים אנשי קשר לחשבון Google",
      "text": "פתחו את אפליקציית 'אנשי קשר' > לחצו על שלוש הנקודות בפינה העליונה > 'הגדרות' > 'העבר אנשי קשר למיקום אחסון אחר' > בחרו מהיכן להעביר וסמנו 'הכל' > לחצו 'בוצע' > בחרו את חשבון Google שלכם כיעד להעברה > לחצו 'העבר' ואשרו.",
      "warning": null
    },
    {
      "title": "יוצרים קיצור דרך לאיש קשר על מסך הבית",
      "text": "פתחו את אפליקציית 'אנשי קשר' > לחצו על איש הקשר הרצוי > לחצו על שלוש הנקודות בפינה העליונה > בחרו 'הוסף למסך הבית' > אשרו.",
      "warning": null
    }
  ]
}